pollination/path/__init__.py
pollination/path/copy.py
pollination/path/read.py
pollination/path/write.py
pollination_path-0.3.4.dist-info/LICENSE
pollination_path-0.3.4.dist-info/METADATA
pollination_path-0.3.4.dist-info/WHEEL
pollination_path-0.3.4.dist-info/top_level.txt
pollination_path-0.3.4.dist-info/RECORD
